KuaileDeLinuxMinglingxing/README.md
KuaileDeLinuxMinglingxing/__init__.py
KuaileDeLinuxMinglingxing/__main__.py
KuaileDeLinuxMinglingxing/file.epub
KuaileDeLinuxMinglingxing/index.html
KuaileDeLinuxMinglingxing/css/__init__.py
KuaileDeLinuxMinglingxing/css/annotations.css
KuaileDeLinuxMinglingxing/css/main.css
KuaileDeLinuxMinglingxing/css/normalize.css
KuaileDeLinuxMinglingxing/css/popup.css
KuaileDeLinuxMinglingxing/font/__init__.py
KuaileDeLinuxMinglingxing/font/fontello.eot
KuaileDeLinuxMinglingxing/font/fontello.svg
KuaileDeLinuxMinglingxing/font/fontello.ttf
KuaileDeLinuxMinglingxing/font/fontello.woff
KuaileDeLinuxMinglingxing/img/__init__.py
KuaileDeLinuxMinglingxing/img/annotator-glyph-sprite.png
KuaileDeLinuxMinglingxing/img/annotator-icon-sprite.png
KuaileDeLinuxMinglingxing/img/apple-touch-icon.png
KuaileDeLinuxMinglingxing/img/cancelfullscreen.png
KuaileDeLinuxMinglingxing/img/close.png
KuaileDeLinuxMinglingxing/img/fullscreen.png
KuaileDeLinuxMinglingxing/img/loader.gif
KuaileDeLinuxMinglingxing/img/menu-icon.png
KuaileDeLinuxMinglingxing/img/save.png
KuaileDeLinuxMinglingxing/img/saved.png
KuaileDeLinuxMinglingxing/img/settings-s.png
KuaileDeLinuxMinglingxing/img/settings.png
KuaileDeLinuxMinglingxing/img/star.png
KuaileDeLinuxMinglingxing/js/__init__.py
KuaileDeLinuxMinglingxing/js/epub.js
KuaileDeLinuxMinglingxing/js/epub.min.js
KuaileDeLinuxMinglingxing/js/epub.min.map
KuaileDeLinuxMinglingxing/js/hooks.min.js
KuaileDeLinuxMinglingxing/js/hooks.min.map
KuaileDeLinuxMinglingxing/js/reader.js
KuaileDeLinuxMinglingxing/js/reader.js.map
KuaileDeLinuxMinglingxing/js/reader.min.js
KuaileDeLinuxMinglingxing/js/reader.min.map
KuaileDeLinuxMinglingxing/js/hooks/__init__.py
KuaileDeLinuxMinglingxing/js/hooks/extensions/__init__.py
KuaileDeLinuxMinglingxing/js/hooks/extensions/highlight.js
KuaileDeLinuxMinglingxing/js/libs/__init__.py
KuaileDeLinuxMinglingxing/js/libs/jquery.min.js
KuaileDeLinuxMinglingxing/js/libs/localforage.min.js
kuaile_de_linux_minglingxing-2024.3.6.0.dist-info/METADATA
kuaile_de_linux_minglingxing-2024.3.6.0.dist-info/WHEEL
kuaile_de_linux_minglingxing-2024.3.6.0.dist-info/entry_points.txt
kuaile_de_linux_minglingxing-2024.3.6.0.dist-info/top_level.txt
kuaile_de_linux_minglingxing-2024.3.6.0.dist-info/RECORD
